LICENSE
MANIFEST.in
README.md
pyproject.toml
setup.cfg
setup.py
amharic_tokenizer/__init__.py
amharic_tokenizer/amh_bpe_v0.2.4.json
amharic_tokenizer/amh_bpe_v0.2.5.json
amharic_tokenizer/cli.py
amharic_tokenizer/fidel_map.py
amharic_tokenizer/pipeline.py
amharic_tokenizer/tokenizer.cpp
amharic_tokenizer/tokenizer.cpython-312-x86_64-linux-gnu.so
amharic_tokenizer/tokenizer.pyx
amharic_tokenizer.egg-info/PKG-INFO
amharic_tokenizer.egg-info/SOURCES.txt
amharic_tokenizer.egg-info/dependency_links.txt
amharic_tokenizer.egg-info/entry_points.txt
amharic_tokenizer.egg-info/top_level.txt
tests/test_basic.py