Metadata-Version: 2.4
Name: amharic-tokenizer
Version: 0.2.5
Summary: Amharic tokenizer with BPE-like merges over decomposed fidel (Cython)
Author: Sefineh Tesfa
Author-email: Sefineh Tesfa <sefinehtesfa34@gmail.com>
License-Expression: MIT
Project-URL: Homepage, https://github.com/sefineh-ai/AMH-Tokenizer
Project-URL: Issues, https://github.com/sefineh-ai/AMH-Tokenizer/issues
Classifier: Programming Language :: Python :: 3
Classifier: Programming Language :: Cython
Classifier: Topic :: Text Processing :: Linguistic
Requires-Python: >=3.8
License-File: LICENSE
Dynamic: author
Dynamic: license-file
Dynamic: requires-python
